imshow/__init__.py
imshow/__main__.py
imshow/_args.py
imshow/_generators.py
imshow/_imshow.py
imshow/_paths.py
imshow/_pyglet.py
imshow/plugins/__init__.py
imshow/plugins/base.py
imshow/plugins/mark.py
imshow/plugins/tile.py
imshow-0.2.4.dist-info/METADATA
imshow-0.2.4.dist-info/WHEEL
imshow-0.2.4.dist-info/entry_points.txt
imshow-0.2.4.dist-info/licenses/LICENSE
imshow-0.2.4.dist-info/RECORD
