Metadata-Version: 2.4
Name: imshow
Version: 0.2.4
Summary: Flexible and Customizable Image Display
Project-URL: Homepage, https://github.com/wkentaro/imshow
Author-email: Kentaro Wada <www.kentaro.wada@gmail.com>
License: MIT
License-File: LICENSE
Keywords: image,visualization
Classifier: Development Status :: 3 - Alpha
Classifier: Environment :: Console
Classifier: Intended Audience :: Developers
Classifier: License :: OSI Approved :: MIT License
Classifier: Operating System :: OS Independent
Classifier: Programming Language :: Python
Classifier: Programming Language :: Python :: 3 :: Only
Classifier: Programming Language :: Python :: 3.8
Classifier: Programming Language :: Python :: 3.9
Classifier: Programming Language :: Python :: 3.10
Classifier: Programming Language :: Python :: 3.11
Classifier: Programming Language :: Python :: 3.12
Classifier: Topic :: Software Development :: Libraries :: Python Modules
Requires-Python: >=3.8
Requires-Dist: imgviz~=1.7.5
Requires-Dist: pyglet~=1.5.31
Provides-Extra: test
Requires-Dist: mypy; extra == 'test'
Requires-Dist: pytest; extra == 'test'
Requires-Dist: ruff; extra == 'test'
Requires-Dist: twine; extra == 'test'
Requires-Dist: types-pillow; extra == 'test'
